{"id": 3195, "text": "Admission Date: 2014-08-30        Discharge Date: 1981-01-24\n\nDate of Birth:  2006-10-26        Sex:  M\n\nService:  NSU\n\n\nHISTORY OF PRESENT ILLNESS:  The patient is a 63-year-old\nright-handed gentleman who was originally diagnosed with\nmelanoma in 2009-01-24.  Since his diagnosis, he\nunderwent a wide excision of the left shin melanoma with\nsentinel lymph node biopsy in 1981-09-23 and\nadditional lymph node removal in 1980-10-09.  He also\nhad stereotactic radiosurgery on 2003-01-20 to a left\nmedial frontal lesion and stereotactic radiosurgery to a\nvermis lesion in 2000-03-11.  Since then, he has developed\nrecurrence of the left frontal brain metastasis versus\nradiation necrosis.  The patient was admitted status post\nleft frontal craniotomy for resection of tumor versus\nnecrosis.\n\nSUMMARY OF HOSPITAL COURSE:  Postoperatively, his vital signs\nwere stable.  He was afebrile.  He was awake, alert, and\noriented times two (to name and place).  He was without\ncomplaints.  He had a slight frontal headache.  His vital\nsigns revealed temperature was 99.6, his heart rate was 69,\nhis blood pressure was 115 to 165/55 to 70, his respiratory\nrate was 12 to 20, and his oxygen saturation was 97 percent\non room air.\n\nThe patient underwent resection of the left frontal\nmetastatic melanoma and radiation necrosis.  His pupils\nequal, round and reactive to light and accommodation.  He had\nno facial asymmetry.  His tongue was midline.  His smile was\nsymmetric.  His sternocleidomastoid strength was greater on\nthe right than on the left.  He had no drift.  His fine\nfinger movements were intact.  His strength was 04-09\nthroughout in all muscle groups.  His sensation was intact to\nlight touch.\n\nHe remained in the Post Anesthesia Care Unit overnight where\nhe remained neurologically stable.  He was oriented to place\nbut not to date.  Naming was intact.  His grasps were full.\nHe had no drift.  He was transferred to the regular floor.\nHe Decadron was slowly weaned.  He was followed by Physical\nTherapy and Occupational Therapy and found to require a short\nrehabilitation stay prior to discharge to home.\n\nHe had a follow-up magnetic resonance imaging scan which\nshowed good excision of the tumor and necrosis.  The patient\nhad slight confusion on postoperative day two.  He had a head\ncomputer tomography which showed no change.  The patient's\nmental status has remained stable.  He was awake, alert, and\noriented times two, but he was sometimes somewhat a little\nconfused; although this was improving.  His balance was still\nsomewhat off, and his safety awareness was slightly\ndecreased.  The patient would benefit for a short\nrehabilitation stay prior to discharge to home.\n\nMEDICATIONS ON DISCHARGE:\n1. Decadron 2 mg by mouth q.8h. for two days and then\n   Decadron 2 mg by mouth q.12h. (starting on 2005-07-19)\n   and stay at this dose.\n2. Percocet one to two tablets by mouth q.4h. as needed.\n3. Famotidine 200 mg by mouth twice per day.\n4. Sertraline 150 mg by mouth once per day.\n5. Atorvastatin 5 mg by mouth once per day.\n6. Hydrochlorothiazide 12.5 mg by mouth once per day.\n7. Ramipril 10 mg by mouth once per day.\n8. Senna one tablet by mouth twice per day as needed.\n9. Colace 100 mg by mouth twice per day.\n10.      Insulin sliding scale - the patient has not required\n   coverage.\n11.      Dilantin 100 mg by mouth three times per day.\n\n\nCONDITION ON DISCHARGE:  The patient's condition was stable\nat the time of discharge.\n\nDISCHARGE FOLLOWUP:  The patient was to follow up in the\nBrain San Juan Regional Rehabilitation Hospital Clinic in two weeks.  The staples should be\nremoved on postoperative day 10; his surgery date was 2014-08-30.  The staples should be removed on 2006-09-27.\n\n\n\n                        [**First Name11 (Name Pattern1) **] Ward, 50347\n\nDictated By:Richardson\nMEDQUIST36\nD:  2013-12-17 15:55:08\nT:  2013-12-17 16:42:54\nJob#:  487\n", "spans": [{"document_id": 3195, "type": ["Medication-related followups"], "start": 2706, "end": 2840}, {"document_id": 3195, "type": ["Appointment-related followup"], "start": 3440, "end": 3565}, {"document_id": 3195, "type": ["Appointment-related followup"], "start": 3656, "end": 3700}]}