{"id": 4292, "text": "Admission Date: 1995-05-15        Discharge Date: 1984-10-13\n\n\nService:  NSU\n\n\nHOSPITAL COURSE:  Ms. Maria Mcconnell Contreras is a [**Age over 90 **]-year-old Chinese-\nspeaking woman who had a fall down 4 steps and hit the back\nof her head.  Son was with the patient and started CPR and\nsaid he felt no pulse.  EMTs arrived and did find patient to\nhave a pulse on the scene.  She had a large laceration on the\nback of her head.  On arrival to the ER she was awake but not\nverbal, was nauseous and vomiting.  She was intubated,\nsedated, and paralyzed and brought to CAT scan.\n\nPast medical history is remarkable for osteoporosis,\nglaucoma, cataracts, and status post cholecystectomy.\n\nMeds are ursodiol.\n\nAllergies are none known.\n\nSOCIAL HISTORY:  She is a nonsmoker, drinks no alcohol.\n\nPHYSICAL EXAMINATION:  Blood pressure was 154/100, heart rate\n100, respiratory 16, 100 percent on 2 liters.  Head, eyes,\nears, nose, and throat showed a large oozing hematoma at the\nocciput.  Lungs were clear bilaterally.  Heart showed regular\nrate and rhythm, normal S1, S2.  Abdomen was soft, nontender.\nBowel sounds were positive.  Neuro:  She was off propofol for\n15 minutes.  She was moving all extremities very strongly,\nattempting to pull at the endotracheal tube.  She is not\nfollowing commands through the Chinese interpreter.  Strength\nwas 10-04 throughout all extremities.  Pupils showed a right\nsurgical pupil.  Left was 2 mm and nonreactive.  Deep tendon\nreflexes were 2 plus bilaterally in the upper and lower\nextremities, and toes were upgoing.\n\nHer hematocrit was 39, sodium was 141, potassium 4.1,\nchloride 102, bicarbonate 26.\n\nCAT scan showed a thin layer of a right subdural with blood\nin the sulci and a right temporal subarachnoid bleed.  There\nwas no shift, no hydrocephalus.  Cervical spine CT showed no\nacute fracture.  Chest x-ray and pelvis x-ray were negative.\nThere was no skull fracture.\n\nPatient was admitted with q. 1-hour neuro checks.  Blood\npressure was recommended to be kept less than 140.  She was\nout of C-spine precautions.  She was loaded with a gram of\nDilantin.\n\nOn 05-24 she did spike a temperature to 102.4 and was\ncultured, and she was requested to get a head CTA to rule out\na carotid dissection, and she also had a repeat head CT\nprior.  She was still not following commands.  The repeat CT\ndid show a slightly enlarged subdural hematoma and the CTA\nshowed no dissection or vascular abnormality.  Repeat CAT\nscan the next day, on the 17th, was stable.\n\nFever workup did show pneumonia, and she was started on\nazithromycin for that.  She was also started on tube feedings\nafter she was extubated on the 17th.  Her neurological exam\ndid slowly improve.  Sedation was stopped and she was allowed\nto wake up.  She had an MRA which was stable, and she was\nthen transferred to the floor.\n\nShe did open her eyes to stimulation but did not follow\ncommands.  She would have purposeful movements of all 4\nextremities.  She did remain in a hard cervical collar.  She\ndid slowly become more awake.  She was seen by both Physical\nTherapy and Occupational Therapy and did well.  A swallowing\nevaluation was attempted on 04-17, but she was too\nsleepy to cooperate but since then has become more awake and\npurposeful and has been able to take p.o. without\ndifficulties.  She did continue to wake up and started to\nfollow visual commands and was nodding \"yes\" and \"no\"\nappropriately and was cooperative with her treatment.  She\ndid continue to slowly improve neurologically.  She will have\na further evaluation by Speech and Swallow.  She has been\nscreened for rehab and will be discharged when bed is\navailable.\n\nDISCHARGE CONDITION:  Neurologically stable.\n\nDISCHARGE DIAGNOSES:\n1. Subdural hematoma.\n2. Pneumonia.\n3. Intracranial hemorrhage.\n\nHer discharge medications are famotidine 30 mg once daily,\nsubcutaneous heparin 5000 units b.i.d.,\noxycodone/acetaminophen elixir 5 to 10 mg p.o. q. 4-6 hours\np.r.n., Dilantin 150 mg p.o. q. 8, Tylenol p.r.n.\n\nShe should follow up with Dr. Wallace in 1 month with\nrepeat head CT.\n\n\n\n                        Mark Greer Gary Martinez, MD 4294\n\nDictated By:Stark\nMEDQUIST36\nD:  1984-10-13 11:21:24\nT:  1984-10-13 11:53:03\nJob#:  950\n", "spans": [{"document_id": 4292, "type": ["Appointment-related followup"], "start": 3496, "end": 3553}, {"document_id": 4292, "type": ["Appointment-related followup", "Imaging-related followup"], "start": 3976, "end": 4045}]}